{"subject_name":"TestSubject","chapters":[{"chapter_name":"Test","topics":[{"topic_name":"NewTopic","topic_html":"<section class=\"col-12 col-md-11 col-lg-9 content-section rounded-2 border\"><h3 class=\"\">Heading</h3><span></span><div data-media-type=\"webpage\" class=\"media-container mb-2 mx-auto box-bg rounded-1 border\"><header class=\"p-2 d-flex jc-between ai-center\"><div class=\"text-truncate fnx-9 flex-grow-1\"><i class=\"fa-solid fa-globe me-1\"></i><span class=\"copy-text\">https://getbootstrap.com/docs/5.3/components/modal/</span></div><div class=\"flex-shrink-0\"><i class=\"fa-light fa-clone mx-1 i-btn rounded-2 copy-btn\"></i><i class=\"fa-solid fa-eye mx-1 i-btn rounded-2 collapsed\" type=\"button\" data-bs-toggle=\"collapse\" data-bs-target=\"#cc4218\" aria-expanded=\"false\" aria-control=\"cc4218\"></i></div></header><iframe class=\"w-100 collapse\" height=\"768px\" id=\"cc4218\" src=\"https://getbootstrap.com/docs/5.3/components/modal/\" style=\"\"></iframe></div><h5 class=\"hl1\">title</h5><p class=\"\">new text</p><div class=\"light-note\">light-note</div><ul class=\"\"><li class=\"\">QDoc</li><li class=\"\">QDoc</li><li class=\"\">QDoc</li></ul><div class=\"math-box p-3 border rounded-2 box-bg my-2\"><math title=\"x_3+y^2=6^3\"><mstyle><msub><mi>x</mi><mn>3</mn></msub><mo>+</mo><msup><mi>y</mi><mn>2</mn></msup><mo>=</mo><msup><mn>6</mn><mn>3</mn></msup></mstyle></math></div></section>","topic_id":208}],"chapter_id":90}],"author":{"login":"Nh-emon","id":146737722,"node_id":"U_kgDOCL8KOg","avatar_url":"https://avatars.githubusercontent.com/u/146737722?v=4","gravatar_id":"","url":"https://api.github.com/users/Nh-emon","html_url":"https://github.com/Nh-emon","followers_url":"https://api.github.com/users/Nh-emon/followers","following_url":"https://api.github.com/users/Nh-emon/following{/other_user}","gists_url":"https://api.github.com/users/Nh-emon/gists{/gist_id}","starred_url":"https://api.github.com/users/Nh-emon/starred{/owner}{/repo}","subscriptions_url":"https://api.github.com/users/Nh-emon/subscriptions","organizations_url":"https://api.github.com/users/Nh-emon/orgs","repos_url":"https://api.github.com/users/Nh-emon/repos","events_url":"https://api.github.com/users/Nh-emon/events{/privacy}","received_events_url":"https://api.github.com/users/Nh-emon/received_events","type":"User","site_admin":false,"name":"Emon","company":null,"blog":"","location":null,"email":null,"hireable":null,"bio":null,"twitter_username":null,"public_repos":20,"public_gists":0,"followers":1,"following":1,"created_at":"2023-10-02T13:07:54Z","updated_at":"2024-08-06T16:33:13Z"}}